djalgo/__init__.py
djalgo/analysis.py
djalgo/conversion.py
djalgo/djai.py
djalgo/fractal.py
djalgo/genetic.py
djalgo/harmony.py
djalgo/loop.py
djalgo/minimalism.py
djalgo/player.py
djalgo/rhythm.py
djalgo/score.py
djalgo/utils.py
djalgo/walk.py
djalgo/data/ca1D_rules.json
djalgo-0.2.11.dist-info/METADATA
djalgo-0.2.11.dist-info/WHEEL
djalgo-0.2.11.dist-info/licenses/LICENSE
djalgo-0.2.11.dist-info/RECORD
