Metadata-Version: 2.3
Name: djalgo
Version: 0.2.11
Summary: A music composition toolkit
Project-URL: Documentation, https://essicolo.github.io/djalgo/
Project-URL: Repository, https://github.com/essicolo/djalgo.git
Project-URL: Bug Tracker, https://github.com/essicolo/djalgo/issues
Author-email: Essi Parent <3pp0qk4a@duck.com>
License: GPL-3.0-or-later
Keywords: midi,music
Classifier: Development Status :: 4 - Beta
Classifier: Intended Audience :: Developers
Classifier: Intended Audience :: Education
Classifier: Intended Audience :: End Users/Desktop
Classifier: License :: OSI Approved :: GNU General Public License v3 (GPLv3)
Classifier: Natural Language :: English
Classifier: Operating System :: OS Independent
Classifier: Programming Language :: Python :: 3
Classifier: Topic :: Multimedia :: Sound/Audio :: MIDI
Requires-Python: >=3.11
Requires-Dist: anywidget
Requires-Dist: matplotlib
Requires-Dist: numpy
Requires-Dist: plotly
Requires-Dist: scipy
Requires-Dist: traitlets
Provides-Extra: ai
Requires-Dist: tensorflow; extra == 'ai'
Provides-Extra: convert
Requires-Dist: mido; extra == 'convert'
Requires-Dist: music21; extra == 'convert'
Requires-Dist: pretty-midi; extra == 'convert'
Provides-Extra: dev
Requires-Dist: bump-my-version; extra == 'dev'
Requires-Dist: furo; extra == 'dev'
Requires-Dist: ipynbname; extra == 'dev'
Requires-Dist: ipywidgets; extra == 'dev'
Requires-Dist: kaleido; extra == 'dev'
Requires-Dist: nbsphinx; extra == 'dev'
Requires-Dist: recommonmark; extra == 'dev'
Requires-Dist: sphinx; extra == 'dev'
Requires-Dist: tomli; extra == 'dev'
Provides-Extra: musician
Requires-Dist: music21; extra == 'musician'
Requires-Dist: pretty-midi; extra == 'musician'
Requires-Dist: scamp; extra == 'musician'
Provides-Extra: notebook
Requires-Dist: ipykernel; extra == 'notebook'
Requires-Dist: ipywidgets; extra == 'notebook'
Requires-Dist: jupyter; extra == 'notebook'
Requires-Dist: jupyterlab; extra == 'notebook'
Requires-Dist: marimo; extra == 'notebook'
